drpsy/__init__.py
drpsy/plotting.py
drpsy/utils.py
drpsy/validate.py
drpsy/batch/__init__.py
drpsy/batch/core.py
drpsy/image/__init__.py
drpsy/image/core.py
drpsy/image/utils.py
drpsy/modeling/__init__.py
drpsy/modeling/core.py
drpsy/modeling/function.py
drpsy/onedspec/__init__.py
drpsy/onedspec/center.py
drpsy/onedspec/core.py
drpsy/onedspec/io.py
drpsy/twodspec/__init__.py
drpsy/twodspec/longslit.py
drpsy/twodspec/utils.py
drpsy-0.0.4.6.dist-info/LICENSE
drpsy-0.0.4.6.dist-info/METADATA
drpsy-0.0.4.6.dist-info/WHEEL
drpsy-0.0.4.6.dist-info/top_level.txt
drpsy-0.0.4.6.dist-info/RECORD
